autofire/__init__.py
autofire/__main__.py
autofire-0.2.dist-info/DESCRIPTION.rst
autofire-0.2.dist-info/METADATA
autofire-0.2.dist-info/RECORD
autofire-0.2.dist-info/WHEEL
autofire-0.2.dist-info/entry_points.txt
autofire-0.2.dist-info/metadata.json
autofire-0.2.dist-info/top_level.txt
