Metadata-Version: 2.0
Name: autofire
Version: 0.2
Summary: CLI for any Python program
Home-page: https://github.com/sslotin/autofire
Author: Sergey Slotin
Author-email: me@sereja.me
License: UNKNOWN
Platform: UNKNOWN
Requires-Dist: fire
